omni_cli/__init__.py
omni_cli/__main__.py
omni_cli/main.py
omni_cli-0.1.0.dist-info/entry_points.txt
omni_cli-0.1.0.dist-info/WHEEL
omni_cli-0.1.0.dist-info/METADATA
omni_cli-0.1.0.dist-info/RECORD
